practice_tests/__init__.py
practice_tests/pr.py
practice_tests-0.1.0.dist-info/METADATA
practice_tests-0.1.0.dist-info/WHEEL
practice_tests-0.1.0.dist-info/top_level.txt
practice_tests-0.1.0.dist-info/RECORD
