Metadata-Version: 2.1
Name: practice_tests
Version: 0.1.0
Summary: A simple SDK to manage names
Author: Rajasekhar Baludu
Author-email: rajasekharbaludu10105@gmail.com
Classifier: Programming Language :: Python :: 3
Classifier: License :: OSI Approved :: MIT License
Classifier: Operating System :: OS Independent
Requires-Python: >=3.6
